gitlab_env/__init__.py
gitlab_env/gitlab_ci_env.py
gitlab_env-0.2.1.dist-info/LICENSE
gitlab_env-0.2.1.dist-info/METADATA
gitlab_env-0.2.1.dist-info/WHEEL
gitlab_env-0.2.1.dist-info/entry_points.txt
gitlab_env-0.2.1.dist-info/RECORD
