Metadata-Version: 2.1
Name: gitlab-env
Version: 0.2.1
Summary: Tool to get/set variables for given Gitlab project
Author: Eugene Aryapov
Author-email: e.aryapov@oom.ag
Requires-Python: >=3.8
Classifier: Programming Language :: Python :: 3
Classifier: Programming Language :: Python :: 3.8
Classifier: Programming Language :: Python :: 3.9
Classifier: Programming Language :: Python :: 3.10
Classifier: Programming Language :: Python :: 3.11
Classifier: Programming Language :: Python :: 3.12
Requires-Dist: GitPython (==3.1.35)
Requires-Dist: python-gitlab (==3.15.0)
Requires-Dist: pyyaml (>=6.0.2,<7.0.0)
